chemxor/__init__.py
chemxor/cli/__init__.py
chemxor/cli/main.py
chemxor/config/__init__.py
chemxor/config/base/catalog/__default__.yml
chemxor/config/base/catalog/cryptic_sage_default.yml
chemxor/config/base/catalog/iris_data_processing.yml
chemxor/config/base/logging.yml
chemxor/config/base/parameters/iris_data_processing.yml
chemxor/config/base/parameters/sm_to_imgs.yml
chemxor/config/local/.gitkeep
chemxor/config/local/credentials.yml
chemxor/data/__init__.py
chemxor/data/enc_conv_dataset.py
chemxor/data/enc_dataset.py
chemxor/data/generic_classification_module.py
chemxor/data/generic_regression_module.py
chemxor/data/mnist.py
chemxor/data/osm.py
chemxor/data/sm_img.py
chemxor/ersilia_output_slim.csv
chemxor/grid_transformer.joblib
chemxor/model/__init__.py
chemxor/model/fhe_activation.py
chemxor/model/fhe_wrapper.py
chemxor/model/olinda_net.py
chemxor/pipeline_registry.py
chemxor/pipelines/__init__.py
chemxor/pipelines/olinda_train_classification.py
chemxor/pipelines/olinda_train_regression.py
chemxor/pipelines/smiles_preprocess.py
chemxor/routes/__init__.py
chemxor/routes/cryptic_sage.py
chemxor/routes/status.py
chemxor/routes/test_encryption.py
chemxor/schema/fhe_model.py
chemxor/schema/test_encryption.py
chemxor/service/__init__.py
chemxor/service/blocs.py
chemxor/service/part_net_client.py
chemxor/service/part_net_server.py
chemxor/settings.py
chemxor/utils.py
chemxor-0.9.0.dist-info/entry_points.txt
chemxor-0.9.0.dist-info/LICENSE
chemxor-0.9.0.dist-info/WHEEL
chemxor-0.9.0.dist-info/METADATA
chemxor-0.9.0.dist-info/RECORD
