Metadata-Version: 2.1
Name: chemxor
Version: 0.9.0
Summary: Privacy Preserving AI/ML for Drug Discovery
License: GPLv3
Author: Ankur Kumar
Author-email: ank@leoank.me
Requires-Python: >=3.8,<3.9
Classifier: License :: Other/Proprietary License
Classifier: Programming Language :: Python :: 3
Classifier: Programming Language :: Python :: 3.8
Requires-Dist: Flask (>=2.1.2,<3.0.0)
Requires-Dist: feather-format (>=0.4.1,<0.5.0)
Requires-Dist: griddify (>=0.0.1,<0.0.2)
Requires-Dist: logzero (>=1.7.0,<2.0.0)
Requires-Dist: pandas (>=1.4,<2.0)
Requires-Dist: protobuf (==3.19.1)
Requires-Dist: pydantic[dotenv] (>=1.8.2,<2.0.0)
Requires-Dist: pytorch-lightning (>=1.6.1,<2.0.0)
Requires-Dist: rdkit-pypi (>=2022.3.1,<2023.0.0)
Requires-Dist: regex (==2022.7.9)
Requires-Dist: tenseal (>=0.3.11,<0.4.0)
Requires-Dist: torch[cpu] (>=1.10.0,<2.0.0)
